{
  "SelectedRFQForComparison": null,
  "SupplierQuotation": [],
  "SupplierQuotationItem": [],
  "ActualSupplierQuotationItem": [],
  "supplierQuotationItemSelected": [],
  "IsEditCompareQuotation": false,
  "compareQuotationIsEditable": false,
  "hasWorkflowApprovalAccess": false,
  "hasWorkflowApprovalEditAccess": false,
  "IsUserAllowedToEdit": false,
  "Mode": "DISPLAY",
  "CompareQuotationHeader": {
    "QuotationComparison": "",
    "RequestForQuotation": "",
    "CompanyCode": "",
    "CompanyName": "",
    "CompativeStatementTitle": "",
    "NameOfRequester": "",
    "AccountAssignment": "",
    "RequisitionNumber": "",
    "RequisitionDate": null,
    "Purpose": "",
    "ComparisonDate": null
  },
  "CompareQuotationItemData": [],
  "CompareQuotationRowsData": [],
  "CompareQuotationTermsConditionData": [],
  "CompareQuotationActualRowsData": [],
  "TermsAndConditionDialog": {
    "IsAddNewTC": false,
    "KeyFieldState": "None",
    "KeyField": "",
    "KeyFieldValueState": "None",
    "KeyFieldValue": "",
    "TermsAndConditionSelectedkey": [],
    "TermsCondPreviousSelectedkey": ["Warranty", "BCDPercent"],
    "PreDefinedTermsAndCondition": [
      {
        "KeyField": "Warranty",
        "KeyFieldDesc": "Warranty",
        "Selectable": true
      },
      {
        "KeyField": "TaxAmount",
        "KeyFieldDesc": "Tax Amount",
        "Selectable": true
      },
      {
        "KeyField": "FreightCharges",
        "KeyFieldDesc": "Freight Charges",
        "Selectable": true
      },
      {
        "KeyField": "Discount",
        "KeyFieldDesc": "Discount",
        "Selectable": true
      },
      {
        "KeyField": "TechnicalCompliance",
        "KeyFieldDesc": "Technical Compliance",
        "Selectable": true
      },
      {
        "KeyField": "InsuranceCharges",
        "KeyFieldDesc": "Insurance Charges",
        "Selectable": true
      },
      {
        "KeyField": "BankCharges",
        "KeyFieldDesc": "Bank Charges",
        "Selectable": true
      },
      {
        "KeyField": "LocalTransportationCharges",
        "KeyFieldDesc": "Local Transportation Charges",
        "Selectable": true
      },
      {
        "KeyField": "LandingCost",
        "KeyFieldDesc": "Landing Cost",
        "Selectable": true
      },
      {
        "KeyField": "Density",
        "KeyFieldDesc": "Density",
        "Selectable": true
      },
      {
        "KeyField": "ContactPerson",
        "KeyFieldDesc": "Contact Person",
        "Selectable": true
      },
      {
        "KeyField": "PhoneNumber",
        "KeyFieldDesc": "Phone Number",
        "Selectable": true
      }
    ]
  },
  "RequestForQuotation": {},
  "RequestForQuotationItem": [],
  "Workflow": {
    "Comment": "",
    "Action": "",
    "CommentState": "None",
    "ReasonCode": "",
    "ReasonCodeState": "None",
    "CurrentTransactionApproverStep": {},
    "WorkFlowTransacationData": [],
    "CurrentDefinationVersion": 1,
    "CurrentTransactionVersion": 1,
    "CurrentWorkflowDefination": [],
    "CurrentWorkflowTransaction": [],
    "RejectionReasonData": [
      {
        "Code": "Reason1",
        "Desc": "Amount is more"
      },
      {
        "Code": "Reason2",
        "Desc": "GST is Very High"
      }
    ]
  },
  "WorkflowDefination": [
    {
      "SeqNo": 1,
      "Rank": 1,
      "versionNo": 1,
      "QuotationComparison": "",
      "StageCode": "INITIATOR_PURCHASE",
      "StageName": "INITIATOR PURCHASE",
      "ApproverType": "User",
      "ApproverValue": "amarjeet.kumar@n-labs.ai",
      "IsMandatory": true,
      "IsActive": true
    },
    {
      "SeqNo": 2,
      "Rank": 2,
      "versionNo": 1,
      "StageCode": "REVIEWER_PURCHASE",
      "StageName": "REVIEWER PURCHASE",
      "ApproverType": "User",
      "ApproverValue": "amarjeet.kumar@n-labs.ai",
      "IsMandatory": true,
      "IsActive": true
    },
    {
      "SeqNo": 3,
      "Rank": 3,
      "versionNo": 1,
      "StageCode": "HOD_PURCHASE",
      "StageName": "HOD PURCHASE",
      "ApproverType": "User",
      "ApproverValue": "amarjeet.kumar@n-labs.ai",
      "IsMandatory": true,
      "IsActive": true
    },
    {
      "SeqNo": 4,
      "Rank": 4,
      "versionNo": 1,
      "StageCode": "TECH_APPROVAL",
      "StageName": "TECH APPROVAL",
      "ApproverType": "User",
      "ApproverValue": "amarjeet.kumar@n-labs.ai",
      "IsMandatory": true,
      "IsActive": true
    },
    {
      "SeqNo": 5,
      "Rank": 5,
      "versionNo": 1,
      "StageCode": "COMM_APPROVAL",
      "StageName": "COMM APPROVAL",
      "ApproverType": "User",
      "ApproverValue": "amarjeet.kumar@n-labs.ai",
      "IsMandatory": true,
      "IsActive": true
    },
    {
      "SeqNo": 6,
      "Rank": 6,
      "versionNo": 1,
      "StageCode": "FINAL_HOD",
      "StageName": "FINAL HOD",
      "ApproverType": "User",
      "ApproverValue": "amarjeet.kumar@n-labs.ai",
      "IsMandatory": true,
      "IsActive": true
    },
    {
      "SeqNo": 7,
      "Rank": 7,
      "versionNo": 1,
      "StageCode": "MANAGING_DIRECTOR",
      "StageName": "MANAGING DIRECTOR",
      "ApproverType": "User",
      "ApproverValue": "amarjeet.kumar@n-labs.ai",
      "IsMandatory": true,
      "IsActive": true
    }
  ],
  "WorkflowTransaction": [],
  "WorkflowApprovers": [
    {
      "StageCode": "INITIATOR_PURCHASE",
      "StageName": "Initiator Purchase",
      "Email": "Subhashini.Kancherla@n-labs.ai",
      "IsActive": true
    },
    {
      "StageCode": "REVIEWER_PURCHASE",
      "StageName": "Reviewer Purchase",
      "Email": "Anudeep.Chittimalla@n-labs.ai",
      "IsActive": true
    },
    {
      "StageCode": "HOD_PURCHASE",
      "StageName": "HOD Purchase",
      "Email": "Sohail.Basha@n-labs.ai",
      "IsActive": true
    },
    {
      "StageCode": "TECH_APPROVAL",
      "StageName": "Technical Approval",
      "Email": "Venkatesh.Erla@n-labs.ai",
      "IsActive": true
    },
    {
      "StageCode": "COMM_APPROVAL",
      "StageName": "Commercial Approval",
      "Email": "Santhosh.Kanaka@n-labs.ai",
      "IsActive": true
    },
    {
      "StageCode": "FINAL_HOD",
      "StageName": "Final HOD Approval",
      "Email": "Vijender.Bajjuri@n-labs.ai",
      "IsActive": true
    },
    {
      "StageCode": "MANAGING_DIRECTOR",
      "StageName": "Managing Director Approval",
      "Email": "Amarjeet.Kumar@n-labs.ai",
      "IsActive": true
    },
    {
      "StageCode": "TECH_APPROVAL",
      "StageName": "Technical Approval",
      "Email": "techlead@n-labs.ai",
      "IsActive": true
    },
    {
      "StageCode": "COMM_APPROVAL",
      "StageName": "Commercial Approval",
      "Email": "commercialhead@n-labs.ai",
      "IsActive": true
    }
  ]
}
